mcp_timeplus/__init__.py
mcp_timeplus/main.py
mcp_timeplus/mcp_env.py
mcp_timeplus/mcp_server.py
mcp_timeplus/prompt_template.py
mcp_timeplus-0.1.6.dist-info/METADATA
mcp_timeplus-0.1.6.dist-info/WHEEL
mcp_timeplus-0.1.6.dist-info/entry_points.txt
mcp_timeplus-0.1.6.dist-info/licenses/LICENSE
mcp_timeplus-0.1.6.dist-info/RECORD
