Metadata-Version: 2.4
Name: mcp-timeplus
Version: 0.1.6
Summary: An MCP server for Timeplus.
Project-URL: Home, https://github.com/jovezhong/mcp-timeplus
License-Expression: Apache-2.0
License-File: LICENSE
Requires-Python: >=3.13
Requires-Dist: confluent-kafka
Requires-Dist: mcp>=1.3.0
Requires-Dist: mcp[cli]>=1.3.0
Requires-Dist: pip-system-certs>=4.0
Requires-Dist: python-dotenv>=1.0.1
Requires-Dist: timeplus-connect>=0.8.15
Requires-Dist: uvicorn>=0.34.0
Provides-Extra: dev
Requires-Dist: pytest; extra == 'dev'
Requires-Dist: ruff; extra == 'dev'
